<annotation verified="no">
  <folder>VOC</folder>
  <filename>10362.jpg</filename>
  <size>
    <width>1360</width>
    <height>1024</height>
    <depth>3</depth>
  </size>
  <object>
    <name>skeletonema</name>
    <pose>Unspecified</pose>
    <truncated>0</truncated>
    <Difficult>0</Difficult>
    <bndbox>
      <xmin>679</xmin>
      <ymin>487</ymin>
      <xmax>777</xmax>
      <ymax>720</ymax>
    </bndbox>
  </object>
  <object>
    <name>thalassionema nitzschioides</name>
    <pose>Unspecified</pose>
    <truncated>0</truncated>
    <Difficult>0</Difficult>
    <bndbox>
      <xmin>917</xmin>
      <ymin>562</ymin>
      <xmax>964</xmax>
      <ymax>613</ymax>
    </bndbox>
  </object>
<object_num>2</object_num></annotation>