<annotation verified="no">
  <folder>VOC</folder>
  <filename>10410.jpg</filename>
  <size>
    <width>1360</width>
    <height>1024</height>
    <depth>3</depth>
  </size>
  <object>
    <name>ceratium fusus</name>
    <pose>Unspecified</pose>
    <truncated>0</truncated>
    <Difficult>0</Difficult>
    <bndbox>
      <xmin>811</xmin>
      <ymin>131</ymin>
      <xmax>914</xmax>
      <ymax>705</ymax>
    </bndbox>
  </object>
  <object>
    <name>helicotheca</name>
    <pose>Unspecified</pose>
    <truncated>0</truncated>
    <Difficult>0</Difficult>
    <bndbox>
      <xmin>85</xmin>
      <ymin>647</ymin>
      <xmax>389</xmax>
      <ymax>856</ymax>
    </bndbox>
  </object>
<object_num>2</object_num></annotation>