<annotation verified="no">
  <folder>VOC</folder>
  <filename>6990.jpg</filename>
  <size>
    <width>1360</width>
    <height>1024</height>
    <depth>3</depth>
  </size>
  <object>
    <name>skeletonema</name>
    <pose>Unspecified</pose>
    <truncated>0</truncated>
    <Difficult>0</Difficult>
    <bndbox>
      <xmin>489</xmin>
      <ymin>790</ymin>
      <xmax>641</xmax>
      <ymax>909</ymax>
    </bndbox>
  </object>
  <object>
    <name>eucampia</name>
    <pose>Unspecified</pose>
    <truncated>0</truncated>
    <Difficult>0</Difficult>
    <bndbox>
      <xmin>976</xmin>
      <ymin>529</ymin>
      <xmax>1103</xmax>
      <ymax>781</ymax>
    </bndbox>
  </object>
  <object>
    <name>chaetoceros</name>
    <pose>Unspecified</pose>
    <truncated>0</truncated>
    <Difficult>0</Difficult>
    <bndbox>
      <xmin>386</xmin>
      <ymin>505</ymin>
      <xmax>591</xmax>
      <ymax>623</ymax>
    </bndbox>
  </object>
<object_num>3</object_num></annotation>