<annotation verified="no">
  <folder>VOC</folder>
  <filename>8549.jpg</filename>
  <size>
    <width>1360</width>
    <height>1024</height>
    <depth>3</depth>
  </size>
  <object>
    <name>guinardia flaccida</name>
    <pose>Unspecified</pose>
    <truncated>0</truncated>
    <Difficult>0</Difficult>
    <bndbox>
      <xmin>181</xmin>
      <ymin>73</ymin>
      <xmax>459</xmax>
      <ymax>926</ymax>
    </bndbox>
  </object>
  <object>
    <name>chaetoceros</name>
    <pose>Unspecified</pose>
    <truncated>0</truncated>
    <Difficult>0</Difficult>
    <bndbox>
      <xmin>936</xmin>
      <ymin>15</ymin>
      <xmax>1042</xmax>
      <ymax>279</ymax>
    </bndbox>
  </object>
<object_num>2</object_num></annotation>