<annotation verified="no">
  <folder>VOC</folder>
  <filename>9965.jpg</filename>
  <size>
    <width>1360</width>
    <height>1024</height>
    <depth>3</depth>
  </size>
  <object>
    <name>dinophysis caudata</name>
    <pose>Unspecified</pose>
    <truncated>0</truncated>
    <Difficult>0</Difficult>
    <bndbox>
      <xmin>1016</xmin>
      <ymin>589</ymin>
      <xmax>1154</xmax>
      <ymax>817</ymax>
    </bndbox>
  </object>
  <object>
    <name>chaetoceros</name>
    <pose>Unspecified</pose>
    <truncated>0</truncated>
    <Difficult>0</Difficult>
    <bndbox>
      <xmin>1104</xmin>
      <ymin>19</ymin>
      <xmax>1327</xmax>
      <ymax>413</ymax>
    </bndbox>
  </object>
<object_num>2</object_num></annotation>